ckanext_metrics_dashboard-0.1.7-nspkg.pth
ckanext/metrics_dashboard/__init__.py
ckanext/metrics_dashboard/plugin.py
ckanext/metrics_dashboard/reports.py
ckanext/metrics_dashboard/templates/report/metrics_dashboard.html
ckanext/metrics_dashboard/templates/report/view.html
ckanext/metrics_dashboard/tests/__init__.py
ckanext/metrics_dashboard/tests/test_reports.py
ckanext_metrics_dashboard-0.1.7.dist-info/LICENSE.md
ckanext_metrics_dashboard-0.1.7.dist-info/METADATA
ckanext_metrics_dashboard-0.1.7.dist-info/WHEEL
ckanext_metrics_dashboard-0.1.7.dist-info/entry_points.txt
ckanext_metrics_dashboard-0.1.7.dist-info/namespace_packages.txt
ckanext_metrics_dashboard-0.1.7.dist-info/top_level.txt
ckanext_metrics_dashboard-0.1.7.dist-info/RECORD
