Metadata-Version: 2.1
Name: ckanext-metrics-dashboard
Version: 0.1.7
Summary: A CKAN extension to display metrics about datasets.
Home-page: https://github.com/GSA/ckanext-metrics_dashboard/
Author: Data.gov
Author-email: datagovhelp@gsa.gov
License: Public Domain
Classifier: Programming Language :: Python :: 3
License-File: LICENSE.md
